ai.py
ifinance.py
inpinitiFinance-1.0.14.dist-info/METADATA
inpinitiFinance-1.0.14.dist-info/WHEEL
inpinitiFinance-1.0.14.dist-info/top_level.txt
inpinitiFinance-1.0.14.dist-info/RECORD
