Metadata-Version: 2.1
Name: inpinitiFinance
Version: 1.0.14
Summary: finance data
Home-page: https://github.com/inpiniti/inpinitiFinance
Author: inpiniti
Author-email: younginpiniti@gmail.com
Keywords: finance,stock,data,inpiniti,dart,krx
